<?xml version="1.0"?>
<monster name="Enyd" description="uma enyd" experience="3400" speed="290" race="undead">
<health now="7100" max="7100"/>
<strategy attack="100" defense="0"/>
<targetchange speed="8000" chance="8"/>
<look type="320" corpse="9916"/>
  
<flags>
	<flag canpushitems="1"/>
	<flag canpushcreatures="1"/>
	<flag hostile="1"/>
	<flag attackable="1"/>
	<flag pushable="0"/>
	<flag staticattack="90"/>
	<flag targetDistance="1"/>
</flags>
  
<attacks>
	<attack name="melee" interval="1800" chance="100" min="-160" max="-256" range="1"/>

	<attack name="speed" interval="3200" chance="15" range="7" target="1" duration="3000" speedchange="-900">
		<attribute key="shootEffect" value="smallstone"/>
		<attribute key="areaEffect" value="stun"/>
	</attack>

	<attack name="earth" interval="3500" chance="45" min="-100" max="-160">
		<attribute key="areaEffect" value="smallplants"/>
	</attack>
	
	<attack name="earth" interval="2200" chance="25" min="-80" max="-150">
		<attribute key="areaEffect" value="bigplants"/>
	</attack>
	
	<attack name="physical" interval="2500" chance="25" min="-100" max="-180">
		<attribute key="areaEffect" value="stones"/>
	</attack>
</attacks>
  
<defenses armor="0" defense="0">
</defenses>
  
<elements><element physicalPercent="5"/>
	<element firePercent="10"/>
	<element earthPercent="95"/>
	<element energyPercent="40"/>
	<element icePercent="25"/>
	<element holyPercent="20"/>
	<element deathPercent="50"/>
</elements>
  
<immunities>
	<immunity paralyze="1"/>
	<immunity invisible="1"/> 
</immunities>
 
<voices speed="5000" chance="10">
	<voice sentence="The sunlight is so depressing." yell="1"/>
	<voice sentence="Come with me, my child." yell="1"/>
	<voice sentence="I've been in the shadow under your bed last night." yell="1"/>
	<voice sentence="You never know what hides in the night."/>
	<voice sentence="I remember your face - and I know where you sleep"/>
</voices>
   
  <loot>
    <item id="2148" countmax="25" chance1="25600"/>
    <item id="2148" countmax="35" chance1="26900"/>
	<item id="6529" countmax="10" chance1="10500"/> 
    <item id="2804" chance="10000"/> 
    <item id="2499" chance="380"/> 
	<item id="7730" chance="50"/> 
    <item id="8869" chance="450"/> 
	<item id="7893" chance="290"/> 
	<item id="2537" chance="280"/> 
    <item id="7407" chance="120"/>         
      
    
  </loot>
</monster>
