<?xml version="1.0"?>
<monster name="Nightstalker" description="a nightstalker" experience="530" speed="260" race="undead">
<health now="700" max="700"/>
<strategy attack="100" defense="0"/>
<targetchange speed="0" chance="8"/>
<look type="320" corpse="9915"/>
  
<flags>
	<flag canpushitems="1"/>
	<flag canpushcreatures="1"/>
	<flag hostile="1"/>
	<flag attackable="1"/>
	<flag pushable="0"/>
	<flag staticattack="90"/>
	<flag targetDistance="1"/>
</flags>
  
<attacks>
	<attack name="melee" interval="1800" chance="100" min="-80" max="-160" range="1"/>

	<attack name="speed" interval="3200" chance="15" range="7" target="1" duration="2000" speedchange="-900">
		<attribute key="areaEffect" value="redshimmer"/>
	</attack>

	<attack name="holy" interval="2300" chance="99" min="-90" max="-160">
		<attribute key="shootEffect" value="holy"/>
	</attack>
</attacks>
  
<defenses armor="0" defense="0">
    <defense name="invisible" interval="7000" chance="20" duration="5000">  7 sec invi duration 5 sec
      <attribute key="areaEffect" value="redshimmer"/>
    </defense>
    <defense name="outfit" interval="2500" chance="20" monster="nightstalker" duration="6000">
      <attribute key="areaEffect" value="blueshimmer"/>
    </defense>
    <defense name="outfit" interval="2500" chance="20" monster="werewolf" duration="6000">
      <attribute key="areaEffect" value="blueshimmer"/>
    </defense>
    <defense name="outfit" interval="2500" chance="20" monster="the count" duration="6000">
      <attribute key="areaEffect" value="blueshimmer"/>
    </defense>
    <defense name="outfit" interval="2500" chance="20" monster="grim reaper" duration="6000">
      <attribute key="areaEffect" value="blueshimmer"/>
    </defense>
    <defense name="outfit" interval="2500" chance="20" monster="tarantula" duration="6000">
      <attribute key="areaEffect" value="blueshimmer"/>
    </defense>
    <defense name="outfit" interval="2500" chance="20" monster="ferumbras" duration="6000">
      <attribute key="areaEffect" value="blueshimmer"/>
    </defense>
</defenses>
  
<elements><element physicalPercent="5"/>
	<element physicalPercent="-25"/>
	<element energyPercent="-15"/>
	<element deathPercent="-5"/>
	<element icePercent="20"/>
	<element holyPercent="10"/>
</elements>
  
<immunities>
	<immunity paralyze="1"/>
	<immunity invisible="1"/> 
</immunities>
 
<voices speed="5000" chance="10">
	<voice sentence="The sunlight is so depressing." yell="1"/>
	<voice sentence="Come with me, my child." yell="1"/>
	<voice sentence="I've been in the shadow under your bed last night." yell="1"/>
	<voice sentence="You never know what hides in the night."/>
	<voice sentence="I remember your face - and I know where you sleep"/>
</voices>
   
  <loot>
    <item id="2148" countmax="65" chance1="25600" chancemax="0"/>
    <item id="2148" countmax="45" chance1="26900" chancemax="0"/>
    <item id="2804" chance="10000"/> 
    <item id="2124" countmax="1" chance1="500"/> 
    <item id="2200" chance="100"/> 
    <item id="2171" chance="210"/> 
    <item id="7407" chance="50"/>         
    <item id="7427" chance="20"/> 
        
    
  </loot>
</monster>
